socrates_ai/__init__.py
socrates_ai-1.3.3.data/data/archive/migration_scripts/add_claude_auth_method_column.sql
socrates_ai-1.3.3.data/data/archive/migration_scripts/add_code_history_column.sql
socrates_ai-1.3.3.data/data/archive/migration_scripts/add_github_import_tables.sql
socrates_ai-1.3.3.data/data/archive/migration_scripts/add_knowledge_documents_columns.sql
socrates_ai-1.3.3.dist-info/licenses/LICENSE
socratic_system/__init__.py
socratic_system/config.py
socratic_system/logging_config.py
socratic_system/monitoring_metrics.py
socratic_system/agents/__init__.py
socratic_system/agents/base.py
socratic_system/agents/code_generator.py
socratic_system/agents/code_validation_agent.py
socratic_system/agents/conflict_detector.py
socratic_system/agents/context_analyzer.py
socratic_system/agents/document_context_analyzer.py
socratic_system/agents/document_processor.py
socratic_system/agents/github_sync_handler.py
socratic_system/agents/knowledge_analysis.py
socratic_system/agents/knowledge_manager.py
socratic_system/agents/learning_agent.py
socratic_system/agents/multi_llm_agent.py
socratic_system/agents/note_manager.py
socratic_system/agents/project_file_loader.py
socratic_system/agents/project_manager.py
socratic_system/agents/quality_controller.py
socratic_system/agents/question_queue_agent.py
socratic_system/agents/socratic_counselor.py
socratic_system/agents/system_monitor.py
socratic_system/agents/test_github_sync_handler.py
socratic_system/agents/user_manager.py
socratic_system/clients/__init__.py
socratic_system/clients/claude_client.py
socratic_system/config/constants.py
socratic_system/config/knowledge_base.json
socratic_system/conflict_resolution/__init__.py
socratic_system/conflict_resolution/base.py
socratic_system/conflict_resolution/checkers.py
socratic_system/conflict_resolution/rules.py
socratic_system/database/__init__.py
socratic_system/database/connection_pool.py
socratic_system/database/embedding_cache.py
socratic_system/database/migration_runner.py
socratic_system/database/project_db.py
socrates_ai-1.3.3.dist-info/METADATA
socrates_ai-1.3.3.dist-info/WHEEL
socrates_ai-1.3.3.dist-info/top_level.txt
socrates_ai-1.3.3.dist-info/RECORD
