Metadata-Version: 2.4
Name: socrates-ai
Version: 1.3.3
Summary: Production-ready collaborative development platform with GitHub-ready project generation, Socratic AI guidance, multi-agent orchestration, real-time collaboration, and RAG knowledge management
Author: Socrates AI Contributors
Maintainer: Socrates AI Contributors
License: MIT
Project-URL: Homepage, https://github.com/Nireus79/Socrates
Project-URL: Documentation, https://github.com/Nireus79/Socrates/tree/master/docs
Project-URL: Repository, https://github.com/Nireus79/Socrates
Project-URL: Source Code, https://github.com/Nireus79/Socrates
Project-URL: Bug Tracker, https://github.com/Nireus79/Socrates/issues
Project-URL: Changelog, https://github.com/Nireus79/Socrates/releases
Project-URL: PyPI Package, https://pypi.org/project/socrates-ai/
Keywords: ai,claude,socratic-method,tutoring,rag,retrieval-augmented-generation,multi-agent,education,software-engineering,collaboration,real-time,knowledge-management,kubernetes,fastapi,postgres,vector-database,chromadb,github,github-ready,export,project-generation,git,ci-cd,github-actions,docker,gitops
Classifier: Development Status :: 5 - Production/Stable
Classifier: Intended Audience :: Developers
Classifier: Intended Audience :: Education
Classifier: License :: OSI Approved :: MIT License
Classifier: Programming Language :: Python :: 3
Classifier: Programming Language :: Python :: 3.8
Classifier: Programming Language :: Python :: 3.9
Classifier: Programming Language :: Python :: 3.10
Classifier: Programming Language :: Python :: 3.11
Classifier: Programming Language :: Python :: 3.12
Classifier: Topic :: Software Development :: Libraries :: Python Modules
Classifier: Topic :: Education
Classifier: Topic :: Scientific/Engineering :: Artificial Intelligence
Classifier: Topic :: Software Development :: Version Control :: Git
Classifier: Topic :: Internet :: WWW/HTTP :: Dynamic Content
Classifier: Framework :: FastAPI
Classifier: Operating System :: OS Independent
Requires-Python: >=3.8
License-File: LICENSE
Requires-Dist: anthropic>=0.40.0
Requires-Dist: chromadb>=0.5.0
Requires-Dist: sentence-transformers>=3.0.0
Requires-Dist: pypdf>=4.0.0
Requires-Dist: python-dateutil>=2.8.0
Requires-Dist: aiosqlite>=0.19.0
Requires-Dist: fastapi>=0.100.0
Requires-Dist: uvicorn[standard]>=0.23.0
Requires-Dist: pydantic>=2.0.0
Requires-Dist: python-dotenv>=1.0.0
Requires-Dist: PyJWT>=2.8.0
Requires-Dist: python-jose>=3.3.0
Requires-Dist: bcrypt>=4.0.0
Requires-Dist: passlib>=1.7.4
Requires-Dist: httpx>=0.24.0
Requires-Dist: sqlalchemy>=2.0.0
Requires-Dist: redis>=5.0.0
Requires-Dist: slowapi>=0.1.9
Requires-Dist: prometheus-client>=0.19.0
Requires-Dist: alembic>=1.12.0
Requires-Dist: gitpython>=3.1.0
Requires-Dist: requests>=2.31.0
Requires-Dist: cryptography>=41.0.0
Requires-Dist: gunicorn>=21.0.0
Requires-Dist: psycopg2-binary>=2.9.0
Provides-Extra: dev
Requires-Dist: pytest>=9.0.0; extra == "dev"
Requires-Dist: pytest-asyncio>=0.24.0; extra == "dev"
Requires-Dist: pytest-cov>=5.0.0; extra == "dev"
Requires-Dist: black>=24.0; extra == "dev"
Requires-Dist: ruff>=0.4.0; extra == "dev"
Requires-Dist: mypy>=1.8.0; extra == "dev"
Requires-Dist: isort>=5.13.0; extra == "dev"
Provides-Extra: async
Requires-Dist: asyncio>=3.4.3; extra == "async"
Provides-Extra: docs
Requires-Dist: sphinx>=5.0; extra == "docs"
Requires-Dist: sphinx-rtd-theme>=1.0; extra == "docs"
Requires-Dist: sphinx-autodoc-typehints>=1.19; extra == "docs"
Dynamic: license-file
